README.md
setup.py
musicdb_client/__init__.py
musicdb_client/api_client.py
musicdb_client/configuration.py
musicdb_client/rest.py
musicdb_client.egg-info/PKG-INFO
musicdb_client.egg-info/SOURCES.txt
musicdb_client.egg-info/dependency_links.txt
musicdb_client.egg-info/requires.txt
musicdb_client.egg-info/top_level.txt
musicdb_client/api/__init__.py
musicdb_client/api/public_api.py
musicdb_client/models/__init__.py
musicdb_client/models/album.py
musicdb_client/models/inline_response200.py
musicdb_client/models/song.py
test/__init__.py
test/test_album.py
test/test_inline_response200.py
test/test_public_api.py
test/test_song.py