Metadata-Version: 1.0
Name: musicdb-client
Version: 1.0.3
Summary: Music Database Server
Home-page: UNKNOWN
Author: UNKNOWN
Author-email: UNKNOWN
License: UNKNOWN
Keywords: Swagger,Music Database Server
Platform: UNKNOWN
